README.rst
setup.cfg
setup.py
micropython_iot/__init__.py
micropython_iot.egg-info/PKG-INFO
micropython_iot.egg-info/SOURCES.txt
micropython_iot.egg-info/dependency_links.txt
micropython_iot.egg-info/top_level.txt
micropython_iot/thingflow/__init__.py
micropython_iot/thingflow/sensors/__init__.py
micropython_iot/thingflow/sensors/adc_esp8266.py